django_runcommands-0.1.dist-info/METADATA
django_runcommands-0.1.dist-info/WHEEL
django_runcommands-0.1.dist-info/top_level.txt
django_runcommands-0.1.dist-info/DESCRIPTION.rst
django_runcommands-0.1.dist-info/pydist.json
django_runcommands-0.1.dist-info/RECORD
runcommands/views.py
runcommands/tests.py
runcommands/test_settings.py
runcommands/models.py
runcommands/__init__.py
runcommands/templates/runcommands/command.html
