Metadata-Version: 2.0
Name: django-runcommands
Version: 0.1
Summary: runcommands: execute system commands from views
Home-page: https://github.com/magopian/django-runcommands
Author: Mathieu Agopian
Author-email: mathieu.agopian@gmail.com
License: BSD Licence
Keywords: s,y,s,t,e,m, ,c,o,m,m,a,n,d,s
Platform: UNKNOWN
Classifier: Development Status :: 3 - Alpha
Classifier: Environment :: Console
Classifier: Intended Audience :: Developers
Classifier: License :: OSI Approved :: BSD License
Classifier: Natural Language :: English
Classifier: Programming Language :: Python
Classifier: Programming Language :: Python :: 2
Classifier: Programming Language :: Python :: 2.7
Classifier: Programming Language :: Python :: 3
Classifier: Programming Language :: Python :: 3.3
